kinto_trello
