Metadata-Version: 1.1
Name: kinto-trello
Version: 0.1.2
Summary: Trello authentication plugin for Kinto
Home-page: https://github.com/francois2metz/kinto-trello
Author: François de Metz
Author-email: francois@2metz.fr
License: MIT
Keywords: kinto trello
Platform: UNKNOWN
Classifier: Development Status :: 3 - Alpha
Classifier: Intended Audience :: Developers
Classifier: Programming Language :: Python :: 3
Classifier: Programming Language :: Python :: 3.3
Classifier: Programming Language :: Python :: 3.4
Classifier: Programming Language :: Python :: 3.5
